{
    "contacts": {
        "messangers": {
            "items": [{
                "name": "WhatsApp"
            }, {
                "name": "Telegram"
            }]
        },
        "phone": "+7 495 946-76-00"
    },
    "apps": {
        "items": [{
            "href": "https://apps.apple.com/ru/app/fitnesson-%D1%81%D0%B5%D1%82%D1%8C-%D1%84%D0%B8%D1%82%D0%BD%D0%B5%D1%81-%D0%BA%D0%BB%D1%83%D0%B1%D0%BE%D0%B2/id1595843755",
            "title": "appstore"
        }, {
            "href": "https://play.google.com/store/apps/details?id=ru.fitnesson.app",
            "title": "goggleplay"
        }]
    },
    "blog": {
        "items": [{
            "id": 0,
            "date": {
                "text": "08.08.2020"
            },
            "category": {
                "text": ""
            },
            "title": {
                "text": ""
            },
            "views": {
                "count": {
                    "value": "1200"
                }
            }
        }]
    },
    "timetable": {
        "items": [{
            "date": {
                "title": {
                    "text": "01.11"
                },
                "subtitle": {
                    "text": "Понедельник"
                }
            },
            "items": [{
                "time": "",
                "category": {
                    "text": ""
                },
                "title": {
                    "text": ""
                },
                "place": "",
                "coach": ""
            }]
        }]
    },
    "clubs": [{
        "data": {
            "id": "0"
        },
        "title": {
            "text": "Владимир"
        },
        "coordinates": [56.128265, 40.394534],
        "address_full": "г.&nbsp;Владимир, октябрьский проспект, д.&nbsp;10, 4-5 этажи",
        "work_hours": { 
            "title": {
                "text": "Время работы"
            },
            "items": [
                "Пн—Вс с 10:00 до 21:00"
            ]
        },
        "tel": "+7 (495) 946–76–09"
    }, {
        "data": {
            "id": "1"
        },
        "title": {
            "text": "Клин"
        },
        "coordinates": [56.331124, 36.713768],
        "address_full": "г.&nbsp;Клин, ул. Карла Маркса, д.&nbsp;6, стр.&nbsp;7, ТЦ «Клинский», 3 этаж",
        "work_hours": {
            "title": {
                "text": "Время работы"
            },
            "items": [
                "Пн—Пт с 07:00 до 24:00,",
                "Сб—Вс 09:00 до 21:00"
            ]
        },
        "tel": "+7 (495) 946–76–09"
    }, {
        "data": {
            "id": "2"
        },
        "title": {
            "text": "Солнечногорск"
        },
        "coordinates": [56.188904, 36.976346],
        "address_full": "г.&nbsp;Солнечногорск, ул.&nbsp;Красная, д.&nbsp;120",
        "work_hours": {
            "title": {
                "text": "Время работы"
            },
            "items": [
                "Пн—Вс, с 10:00 до 21:00"
            ]
        },
        "tel": "+7 (495) 946–76–09"
    }, {
        "data": {
            "id": "3"
        },
        "title": {
            "text": "Электросталь"
        },
        "coordinates": [55.796521, 38.440896],
        "address_full": "г.&nbsp;Электросталь, пр-т.&nbsp;Ленина, д.&nbsp;25а",
        "work_hours": {
            "title": {
                "text": "Время работы"
            },
            "items": [
                "Пн—Вс, с 10:00 до 21:00"
            ]
        },
        "tel": "+7 (495) 946–76–09"
    }, {
        "data": {
            "id": "4"
        },
        "title": {
            "text": "Орехово–зуево"
        },
        "coordinates": [55.812757, 38.999559],
        "address_full": "г.&nbsp;Орехово-Зуево, ул.&nbsp;Ленина, д.&nbsp;121, ТЦ Остров",
        "work_hours": {
            "title": {
                "text": "Время работы"
            },
            "items": [
                "Пн—Вс, с 10:00 до 21:00"
            ]
        },
        "tel": "+7 (495) 946–76–09"
    }, {
        "data": {
            "id": "5"
        },
        "title": {
            "text": "Звенигород"
        },
        "coordinates": [55.730061, 36.853259],
        "address_full": "г.&nbsp;Звенигород, ул.&nbsp;Московская, д.&nbsp;12",
        "work_hours": {
            "title": {
                "text": "Время работы"
            },
            "items": [
                "Пн—Вс, с 10:00 до 21:00"
            ]
        },
        "tel": "+7 (495) 946–76–09"
    }, {
        "data": {
            "id": "6"
        },
        "title": {
            "text": "Краснознаменск"
        },
        "coordinates": [55.594962, 37.038932],
        "address_full": "г.&nbsp;Краснознаменск, ул. Краснознаменная, 23",
        "work_hours": {
            "title": {
                "text": "Время работы"
            },
            "items": [
                "Пн—Вс, с 10:00 до 21:00"
            ]
        },
        "tel": "+7 (495) 946–76–09"
    }, {
        "data": {
            "id": "7"
        },
        "title": {
            "text": "Голицыно"
        },
        "coordinates": [55.629323, 37.011659],
        "address_full": "Московская область, Большие Вяземы, пос.&nbsp;Школьный, 12&nbsp;А",
        "work_hours": {
            "title": {
                "text": "Время работы"
            },
            "items": [
                "Пн-Пт 7:00-24:00",
                "Сб-Вс 9:00-22:00"
            ]
        },
        "tel": "+7 (495) 946–76–03"
    }],
    "promo": {
        "img": {
            "src": "https://i.ibb.co/b52YmnW/promo.jpg"
        },
        "content": {
            "title": {
                "text": "Мы создали <span>уникальную концепцию</span> фитнес клуба"
            },
            "boxLink": {
                "text": "Подарочная Персональная Тренировка",
                "anchor": ""
            },
            "numbers": {
                "items": [{
                    "title": {
                        "text": "в 2 раза"
                    },
                    "descr": "эффективнее классического фитнес клуба"
                }, {
                    "title": {
                        "text": "10 000"
                    },
                    "descr": "ежемесячно выбирают наши фитнес клубы"
                }, {
                    "title": {
                        "text": "10"
                    },
                    "descr": "лет успешной работы"
                }]
            }
        }
    },
    "sale": {
        "slider": {
            "component": "SaleArticle",
            "items": [{
                "id": 0,
                "img": {
                    "src": "https://i.ibb.co/G5XHQDb/sale.jpg"
                },
                "content": {
                    "title": {
                        "text": "Осенние скидки <span>от 17% до 33%</span>"
                    },
                    "text": "Осень, пожалуй, лучшее время года, чтобы заняться спортом! В наших клубах всегда радужная атмосфера, энергичная обстановка и теплая сауна.",
                    "btn": {
                        "href": "#",
                        "text": "Подробнее об акции"
                    }
                }
            }, {
                "id": 1,
                "img": {
                    "src": "https://i.ibb.co/NpZ6vR9/club-benefits.jpg"
                },
                "content": {
                    "title": {
                        "text": "Осенние скидки <span>от 17% до 33%</span>"
                    },
                    "text": "Осень, пожалуй, лучшее время года, чтобы заняться спортом! В наших клубах всегда радужная атмосфера, энергичная обстановка и теплая сауна.",
                    "btn": {
                        "href": "#",
                        "text": "Подробнее об акции"
                    }
                }
            }, {
                "id": 2,
                "img": {
                    "src": "https://i.ibb.co/7r3rXMH/event.jpg"
                },
                "content": {
                    "title": {
                        "text": "Осенние скидки <span>от 17% до 33%</span>"
                    },
                    "text": "Осень, пожалуй, лучшее время года, чтобы заняться спортом! В наших клубах всегда радужная атмосфера, энергичная обстановка и теплая сауна.",
                    "btn": {
                        "href": "#",
                        "text": "Подробнее об акции"
                    }
                }
            }]
        }
    },
    "unique_concept": {
        "title": {
            "text": "Уникальная концепция FITNESSON"
        },
        "img": {
            "src": "https://i.ibb.co/RhxGD8J/img.jpg"
        },
        "video": {
            "href": "https://www.youtube.com/watch?v=TxZYXAAvPvo",
            "img": {
                "src": "https://i.ibb.co/ZzB2p4v/video.jpg"
            },
            "info": {
                "items": [{
                    "text": "Видео"
                }, {
                    "text": "2 минуты,"
                }, {
                    "text": "12 секунд"
                }]
            }
        },
        "textBlock": {
            "items": [{
                "id": 0,
                "text": "Мы поняли, что классические фитнес клубы отлично зарабатывают деньги владельцу, но забывают о результатах клиентов, поэтому неэффективны."
            }, {
                "id": 1,
                "text": "Мы изменили подход, придумали фитнес клуб заново. Создали концепцию, где наши клиенты добиваются результатов и обретают желанную форму. В каждую карту включен тренер наставник. Диагностируем, составляем план тренировок и питания. Следим за успехами и корректируем цели клиентов. Разработали собственное фитнес приложение."
            }, {
                "id": 2,
                "text": "FITNESSON — это уникальный фитнес клуб, аналогов которому нет в России."
            }]
        },
        "form": {
            "title": {
                "text": "Узнайте больше о фитнес клубе FITNESSON"
            },
            "fieldBg": "light-blue",
            "fields": [{
                "placeholder": "Имя",
                "required": true
            }, {
                "type": "tel",
                "placeholder": "Телефон",
                "required": true
            }],
            "btn": {
                "type": "submit",
                "text": "Отправить заявку"
            },
            "agree": true
        },
        "asideClient": {
            "gender": "male",
            "name": "Дмитрий Борисов",
            "direction": "reverse"
        }
    },
    "mobile_app": {
        "img": {
            "src": "https://i.ibb.co/tqyHY1s/bg.jpg"
        },
        "title": {
            "text": "Мобильное приложение FITNESSON"
        },
        "textBlock": {
            "items": [{
                "id": 0,
                "bold": true,
                "text": "Мы сделали IT платформу для обычных людей. Мобильное приложение для клиентов и систему управления для тренеров."
            }, {
                "id": 1,
                "text": "Тренер видит ваш результат и корректирует тренировочный процесс. Вы используете удобный инструмент для работы в зале и за его пределами."
            }]
        }
    },
    "events": {
        "top": {
            "suptitle": {
                "text": "Fitness-On проводит дни открытых дверей, мастер-классы и семинары по спорту"
            },
            "title": {
                "text": "Мероприятия <span>и события</span>"
            }
        },
        "items": [{
            "img": {
                "src": "https://i.ibb.co/yNxGFHR/img.jpg"
            },
            "content": {
                "title": {
                    "text": "Проект по эффективному похудению «Невесомость»"
                },
                "textBlock": {
                    "items": [{
                        "id": 0,
                        "text": "Целью проекта «Невесомость» является помощь людям, не имеющим возможности самостоятельно справится с проблемой излишнего веса."
                    }]
                },
                "leader": {
                    "items": [{
                        "id": 0,
                        "key": "Дата и время",
                        "value": {
                            "datetime": {
                                "date": "2022-11-10",
                                "time": "11:00",
                                "text": "10 ноября 11:00"
                            }
                        }
                    }, {
                        "id": 1,
                        "key": "Телефон",
                        "value": {
                            "phone": "+7 (495) 946-76-07"
                        }
                    }, {
                        "id": 2,
                        "key": "Адрес",
                        "value": {
                            "items": [{
                                "text": "FITNESSON Электросталь"
                            }, {
                                "text": "г. Электросталь, пр-т. Ленина, д. 25а"
                            }]
                        }
                    }]
                },
                "btn": {
                    "text": "Подробнее"
                }
            }
        }]
    },
    "free_training": {
        "title": {
            "text": "Бесплатное занятие с тренером"
        },
        "textBlock": {
            "items": [{
                "id": 0,
                "text": "В FITNESSON это не просто разовый визит в клуб — у нас это гораздо больше! Бесплатное занятие с тренером ни к чему не обязывает."
            }, {
                "id": 0,
                "text": "Его цель - причинить вам пользу и познакомить с уникальной концепцией FITNESSON и услугами клуба."
            }]
        },
        "img": {
            "src": "https://i.ibb.co/1ZRsLPp/coach.png"
        },
        "video": {
            "href": "https://www.youtube.com/watch?v=TxZYXAAvPvo",
            "img": {
                "src": "https://i.ibb.co/bgZzxWk/video.jpg"
            },
            "box": {
                "text": "Посмотрите процесс"
            },
            "info": {
                "items": [{
                    "text": "Видео"
                }, {
                    "text": "2 мин, 14 сек"
                }]
            }
        },
        "list": {
            "items": [{
                "text": "Сделают анализ тела на профессиональном анализаторе InBody."
            }, {
                "text": "Тренер проведет полноценную тренировку."
            }, {
                "text": "Проконсультируем по правильному питанию."
            }, {
                "text": "Познакомим с уникальной концепцией FITNESSON."
            }]
        }
    },
    "free_training_recording": {
        "title": {
            "text": "Запишитесь <span>на бесплатную</span> тренировку с тренером"
        },
        "textBlock": {
            "items": [{
                "id": 0,
                "text": "Наши менеджеры позвонят вам, расскажут про все детали и ответят на вопросы."
            }]
        },
        "form": {
            "fields": [{
                "placeholder": "Имя",
                "required": true
            }, {
                "type": "tel",
                "placeholder": "Телефон",
                "required": true
            }, {
                "name": "select",
                "placeholder": "Выберите клуб",
                "options": [{

                }]
            }],
            "btn": {
                "text": "Отправить"
            },
            "agree": true
        }
    }
}